game_of_life/__init__.py
game_of_life/__main__.py
game_of_life/cli.py
game_of_life/model.py
game_of_life/presenter.py
game_of_life/view.py
game_of_life_nodeps-0.0.3.dist-info/LICENSE.txt
game_of_life_nodeps-0.0.3.dist-info/METADATA
game_of_life_nodeps-0.0.3.dist-info/WHEEL
game_of_life_nodeps-0.0.3.dist-info/entry_points.txt
game_of_life_nodeps-0.0.3.dist-info/top_level.txt
game_of_life_nodeps-0.0.3.dist-info/RECORD
