Metadata-Version: 2.1
Name: game-of-life-nodeps
Version: 0.0.3
Summary: Game of Life with only Python builtin libraries
Home-page: https://github.com/johnliu55tw/game-of-life
Author: John Liu
Author-email: johnliu55tw@gmail.com
License: UNKNOWN
Keywords: game-of-life tk tkinter simple
Platform: UNKNOWN
